codepage/__init__.py
codepage/__main__.py
codepage/pyrustic_data/backstage/config/build.json
codepage/pyrustic_data/backstage/config/init.json
codepage/pyrustic_data/backstage/config/release.json
codepage/pyrustic_data/backstage/data/github_release_form.json
codepage/pyrustic_data/backstage/report/build_report.json
codepage/pyrustic_data/backstage/report/release_report.json
codepage/pyrustic_data/hubstore/img.json
codepage/pyrustic_data/hubstore/promotion.json
tests/__init__.py
codepage-0.0.1.dist-info/LICENSE
codepage-0.0.1.dist-info/METADATA
codepage-0.0.1.dist-info/WHEEL
codepage-0.0.1.dist-info/entry_points.txt
codepage-0.0.1.dist-info/top_level.txt
codepage-0.0.1.dist-info/RECORD
